anyside/__init__.py
anyside/anyside.py
Anyside-0.0.6.dist-info/METADATA
Anyside-0.0.6.dist-info/WHEEL
Anyside-0.0.6.dist-info/top_level.txt
Anyside-0.0.6.dist-info/RECORD
