Metadata-Version: 2.1
Name: Anyside
Version: 0.0.6
Summary: Anyside Python API
Home-page: UNKNOWN
Author: Anyside
Author-email: <developer@anyside.com>
License: UNKNOWN
Keywords: python,anyside
Platform: UNKNOWN
Classifier: Development Status :: 1 - Planning
Classifier: Intended Audience :: Developers
Classifier: Programming Language :: Python :: 3
Classifier: Operating System :: Unix
Classifier: Operating System :: MacOS :: MacOS X
Classifier: Operating System :: Microsoft :: Windows
Requires-Dist: requests
